{
  "id": "e2f1f4269508a02a812321a9e3c3f5fa",
  "userId": "6880d80fe7f995e87c47d26f",
  "meditationType": "sleep",
  "language": "fr",
  "text": "Bienvenue dans cette gyhrelaxation musculaire progressive pour le sommeil... Cette pratique vous aidera à relâcher la tension physique et à préparer votre corps pour un repos profond... Trouvez une position confortable et fermez les yeux... Nous allons systématiquement détendre chaque muscle de votre corps...\n\nCommencez par trois respirations profondes et libératrices... Inspirez lentement par le nez... Retenez un moment... Puis expirez complètement par la bouche... relâchant la journée... ... Encore une fois... respirez profondément... sentez votre corps s'expandre... Retenez... et relâchez avec une longue expiration lente... ... Une fois de plus... inspirez la paix... retenez... expirez toute tension... Maintenant laissez votre respiration devenir naturelle et facile......\n\nNous allons maintenant contracter et relâcher chaque groupe musculaire... Cela aide votre corps à apprendre la différence entre tension et relaxation... D'abord... concentrez-vous sur vos pieds... Contractez vos orteils fortement... Maintenez pendant cinq secondes... un... deux... trois... quatre... cinq...... Maintenant relâchez... Sentez la relaxation inonder vos pieds... ... Ensuite... contractez vos muscles des mollets... Serrez-les fort... Maintenez... un... deux... trois... quatre... cinq...... Et relâchez... Sentez la tension qui fond......\n\nMaintenant contractez vos muscles des cuisses... Serrez-les aussi fort que possible... Maintenez pendant cinq... quatre... trois... deux... un... Et relâchez complètement... Sentez le soulagement... ... Serrez vos poings... Maintenez-les serrés... cinq... quatre... trois... deux... un... Relâchez et sentez vos bras devenir lourds et détendus... ... Contractez vos muscles des épaules... Montez-les vers vos oreilles... Maintenez... Et laissez-les tomber... Sentez le relâchement... ... Contractez les muscles de votre visage... Fermez fort vos yeux... Maintenez... Et relâchez complètement... Laissez votre visage devenir doux et paisible......\n\nMaintenant que chaque muscle de votre corps a été contracté et relâché... Sentez la relaxation profonde dans tout votre corps... Vos pieds sont complètement détendus... Vos jambes sont lourdes et à l'aise... Vos bras sont relâchés et confortables... Votre visage est doux et paisible... ... Remarquez comme la relaxation est différente de la tension... C'est l'état naturel de repos de votre corps... Laissez-vous sombrer plus profondément dans cette sensation paisible......\n\nVotre corps est maintenant complètement préparé pour le sommeil... Chaque muscle est détendu et à l'aise... Vous avez relâché toute la tension de votre journée... ... Il est sûr de lâcher prise complètement maintenant... Votre corps sait comment se reposer et se réparer... Vous méritez ce sommeil paisible... ... Faites confiance à la sagesse naturelle de votre corps... Permettez-vous de dériver dans un sommeil profond et réparateur......\n\nReposez-vous ici dans cet état de relaxation profonde... Votre corps est lourd et confortable... Votre esprit est calme et silencieux... ... Laissez cette relaxation vous porter dans un sommeil paisible... Dormez profondément... Reposez-vous complètement... Et réveillez-vous en vous sentant rafraîchi et renouvelé... Bonne nuit......",
  "createdAt": "2025-07-23T13:52:52.211Z",
  "updatedAt": "2025-07-23T13:52:52.211Z"
}