{
  "id": "125c74c26ba91874b49059fff1012804",
  "userId": "687d36a19a34cd2d0276bfc7",
  "meditationType": "sleep",
  "language": "nl",
  "text": "Welkom bij deze rustgevende oceaan slaapmeditatie... Nestel je comfortabel in je bed... Sluit je ogen en stel je voor dat je ligt op een prachtig strand bij zonsondergang... Het geluid van zachte golven zal je naar een vredige slaap leiden...\n\nBegin met diep ademhalen... Inademen van de frisse zeelucht... voel hoe deze je longen volledig vult... Langzaam uitademen... laat alle spanning van de dag los... ... Luister naar het ritme van de golven... In... en uit... In... en uit... Laat je ademhaling dit natuurlijke ritme volgen... Elke ademhaling brengt je dieper in ontspanning......\n\nStel je voor dat je ligt op warm... zacht zand... De zon gaat onder en schildert de lucht in prachtige kleuren... Je hoort het zachte geluid van golven die op de kust rollen... Elke golf spoelt je zorgen en stress weg... ... Voel het warme zand dat je lichaam ondersteunt... De zachte zeebries die je huid streelt... Je bent hier volledig veilig en vredig... ... Met elke golf die binnenkomt... voel je je slaperig... meer ontspannen... De oceaan zingt je in slaap......\n\nLaat nu de golven over je lichaam spoelen... Begin met je voeten... Voel hoe ze zo zwaar worden als nat zand... De golven stromen omhoog door je benen... maken ze volledig ontspannen en zwaar... ... Het zachte water stroomt over je heupen en onderrug... Alle spanning smelt weg zoals zand dat glad wordt gemaakt door het getij... Je armen drijven vredig... zwaar en ontspannen... ... Voel de golven over je borst spoelen... je schouders... je nek... Je gezicht wordt zacht en vredig... volledig ontspannen......\n\nMet elke golf weet je... Je bent veilig en beschermd... De oceaan houdt je zachtjes vast... Je bent in perfecte vrede... ... Je lichaam is klaar voor diepe... rustgevende slaap... De golven dragen al je zorgen weg... Morgen brengt nieuwe mogelijkheden... ... Op dit moment is er alleen vrede... alleen rust... alleen het zachte geluid van golven......\n\nBlijf hier rusten op dit vredige strand... De golven zetten hun zachte ritme voort... wiegen je in slaap... ... Laat het geluid van de oceaan je meenemen naar prachtige dromen... Slaap diep... Rust volledig... En word verfrist wakker als de dageraad over de oceaan... Welterusten......",
  "audioFiles": [
    {
      "filename": "meditation_nl_1753036804509_5b1046a5.mp3",
      "voiceId": "nl-NL-Wavenet-D",
      "background": "ocean",
      "duration": 257.568,
      "language": "nl"
    }
  ],
  "createdAt": "2025-07-20T18:40:04.620Z",
  "updatedAt": "2025-07-20T18:40:04.620Z"
}